my_module.py
hardy_lib/__init__.py
hardy_lib/run_func.py
hardytestlib-1.0.0.dist-info/LICENSE.txt
hardytestlib-1.0.0.dist-info/METADATA
hardytestlib-1.0.0.dist-info/WHEEL
hardytestlib-1.0.0.dist-info/top_level.txt
hardytestlib-1.0.0.dist-info/RECORD
