Metadata-Version: 2.1
Name: hardytestlib
Version: 1.0.0
Summary: this is a very niubi lib
Home-page: https://github.com/hardy9sap
Author: hardy9sap
Author-email: hardy9sap@163.com
License: MIT
Platform: UNKNOWN
